RaspberryMotors/__init__.py
RaspberryMotors/example_advanced_servo.py
RaspberryMotors/example_simple_2servos.py
RaspberryMotors/example_simple_servo.py
RaspberryMotors/example_timer_servo.py
RaspberryMotors/motors/__init__.py
RaspberryMotors/motors/__main__.py
RaspberryMotors/motors/servos.py
RaspberryMotors-1.0.3.dist-info/LICENSE
RaspberryMotors-1.0.3.dist-info/METADATA
RaspberryMotors-1.0.3.dist-info/WHEEL
RaspberryMotors-1.0.3.dist-info/top_level.txt
RaspberryMotors-1.0.3.dist-info/RECORD
