Metadata-Version: 2.1
Name: RaspberryMotors
Version: 1.0.3
Summary: Raspberry Pi service library dedicated to motor control
Home-page: https://github.com/pypa/sampleproject
Author: Vikram Dayal
Author-email: vdayal@avman.net
License: UNKNOWN
Project-URL: Bug Tracker, https://github.com/vikramdayal/RaspberryMotors/issues
Platform: UNKNOWN
Classifier: Programming Language :: Python :: 3
Classifier: License :: OSI Approved :: MIT License
Classifier: Operating System :: OS Independent
Requires-Python: >=3.6
